AdminCustomFilter/__init__.py
AdminCustomFilter/asgi.py
AdminCustomFilter/settings.py
AdminCustomFilter/urls.py
AdminCustomFilter/wsgi.py
admin_custom_filter/__init__.py
admin_custom_filter/admin.py
admin_custom_filter/admin_filter.py
admin_custom_filter/apps.py
admin_custom_filter/models.py
admin_custom_filter/tests.py
admin_custom_filter/views.py
admin_custom_filter/migrations/__init__.py
admin_custom_filter/templates/admin/change_list.html
authentication/__init__.py
authentication/admin.py
authentication/apps.py
authentication/models.py
authentication/tests.py
authentication/views.py
authentication/migrations/0001_initial.py
authentication/migrations/__init__.py
countries/__init__.py
countries/admin.py
countries/apps.py
countries/models.py
countries/tests.py
countries/views.py
countries/migrations/0001_initial.py
countries/migrations/0002_street.py
countries/migrations/__init__.py
admin_custom_filter-1.0.8.dist-info/METADATA
admin_custom_filter-1.0.8.dist-info/WHEEL
admin_custom_filter-1.0.8.dist-info/top_level.txt
admin_custom_filter-1.0.8.dist-info/RECORD
