Metadata-Version: 2.1
Name: admin_custom_filter
Version: 1.0.8
Home-page: https://github.com/i3z101/admin_custom_filter/tree/master
Author: Abdulaziz Baqaleb
Author-email: ab.ah.bq@gmail.com
Maintainer: Abdulaziz Baqaleb
Maintainer-email: ab.ah.bq@gmail.com
License: MIT License
Requires-Dist: django-bleach>=3.1.0
Requires-Dist: bleach>=5.0.1
